{
  "name": "mitigation_cb-315mt-led~0012",
  "data": [
    {
      "seriesName": "SH2PCELC_01",
      "seriesValues": [
        [
          2023,
          0.00012165977753708148
        ],
        [
          2024,
          0.00020142707679480875
        ],
        [
          2025,
          0.0005069467758871785
        ],
        [
          2026,
          2.632129748477455e-05
        ],
        [
          2027,
          2.801665933847946e-05
        ],
        [
          2028,
          3.2705834842888646e-05
        ],
        [
          2029,
          0.0008921640676736898
        ],
        [
          2030,
          0.16208309730147427
        ],
        [
          2031,
          0.19278626277908795
        ],
        [
          2032,
          0.3454207669880668
        ],
        [
          2033,
          6.101125533976572
        ],
        [
          2034,
          6.512202329036291
        ],
        [
          2035,
          1.5513072609295595
        ],
        [
          2036,
          1.7288779057591994
        ],
        [
          2037,
          2.6011981431274998
        ],
        [
          2038,
          3.1498203387260633
        ],
        [
          2039,
          3.777217893510341
        ],
        [
          2040,
          6.5663655637034335
        ],
        [
          2041,
          12.62011229284595
        ],
        [
          2042,
          12.729435175740084
        ],
        [
          2043,
          12.919861251909614
        ],
        [
          2044,
          12.94238342987723
        ],
        [
          2045,
          13.061844743394792
        ],
        [
          2046,
          13.4221512802922
        ],
        [
          2047,
          13.596460960118147
        ],
        [
          2048,
          13.423504680783457
        ],
        [
          2049,
          14.165739172392552
        ],
        [
          2050,
          13.911210026052345
        ],
        [
          2051,
          12.90968128030047
        ]
      ]
    },
    {
      "seriesName": "SH2PDELC_01",
      "seriesValues": [
        [
          2023,
          1.2748331890803842e-05
        ],
        [
          2024,
          2.636855109349762e-05
        ],
        [
          2025,
          6.994758802705653e-05
        ],
        [
          2026,
          1.845681293337416e-05
        ],
        [
          2027,
          2.0882332181566577e-05
        ],
        [
          2028,
          2.5246254608766486e-05
        ],
        [
          2029,
          0.00015337892221462476
        ],
        [
          2030,
          0.3510128749200069
        ],
        [
          2031,
          0.4127370291428192
        ],
        [
          2032,
          0.6415851753016617
        ],
        [
          2033,
          0.6734488374658886
        ],
        [
          2034,
          0.7029080479048477
        ],
        [
          2035,
          0.4264789860348975
        ],
        [
          2036,
          0.533612798683534
        ],
        [
          2037,
          0.6056271533963324
        ],
        [
          2038,
          0.6092061723409695
        ],
        [
          2039,
          0.8182069381493785
        ],
        [
          2040,
          0.834176357232402
        ],
        [
          2041,
          0.8486972357747524
        ],
        [
          2042,
          0.8617128959040042
        ],
        [
          2043,
          0.8735994465886388
        ],
        [
          2044,
          0.8841718643429722
        ],
        [
          2045,
          0.8950873935902398
        ],
        [
          2046,
          0.9059436051349651
        ],
        [
          2047,
          0.9146599971066207
        ],
        [
          2048,
          0.9212386304456662
        ],
        [
          2049,
          0.9256726160376739
        ],
        [
          2050,
          0.9117204818295231
        ],
        [
          2051,
          0.9068571992365773
        ]
      ]
    }
  ]
}